PythonReports/PILDrivers.py
PythonReports/RLDrivers.py
PythonReports/Tk.py
PythonReports/TkDrivers.py
PythonReports/__init__.py
PythonReports/api.py
PythonReports/aztec_code_generator.py
PythonReports/barcode.py
PythonReports/builder.py
PythonReports/datatypes.py
PythonReports/design.py
PythonReports/drivers.py
PythonReports/fonts.py
PythonReports/pdf.py
PythonReports/printout.py
PythonReports/rson.py
PythonReports/segment_layout.py
PythonReports/template.py
PythonReports/version.py
PythonReports/windows_fonts.py
PythonReports/wxDrivers.py
PythonReports/wxPrint.py
PythonReports-1.0.0.dist-info/METADATA
PythonReports-1.0.0.dist-info/WHEEL
PythonReports-1.0.0.dist-info/entry_points.txt
PythonReports-1.0.0.dist-info/RECORD