Metadata-Version: 2.1
Name: PythonReports
Version: 1.0.0
Summary: Database report generator
Author: Aleksandr Smyshliaev, Alexey Luchko, KACAH
Maintainer: PythonReports Users Mailing List
Maintainer-email: pythonreports-users@lists.sourceforge.net
Classifier: Development Status :: 5 - Production/Stable
Classifier: Intended Audience :: Developers
Classifier: Intended Audience :: Information Technology
Classifier: License :: OSI Approved :: MIT License
Classifier: Operating System :: OS Independent
Classifier: Programming Language :: Python :: 3
Classifier: Topic :: Printing
Project-URL: Homepage, https://pythonreports.sourceforge.net/
Project-URL: Repository, https://sourceforge.net/p/pythonreports/code/
Requires-Dist: Pillow
Requires-Dist: qrcode
Requires-Dist: ReportLab
Requires-Dist: rsonlite
